agl_frame_extractor/__init__.py
agl_frame_extractor/extractor.py
agl_frame_extractor-0.2.1.dist-info/LICENSE
agl_frame_extractor-0.2.1.dist-info/METADATA
agl_frame_extractor-0.2.1.dist-info/WHEEL
agl_frame_extractor-0.2.1.dist-info/RECORD
