Metadata-Version: 2.1
Name: agl-frame-extractor
Version: 0.2.1
Summary: Extracts frames from .mov files
Author: Thomas J. Lux
Author-email: lux_t1@ukw.de
Requires-Python: >=3.11,<4.0
Classifier: Programming Language :: Python :: 3
Classifier: Programming Language :: Python :: 3.11
Classifier: Programming Language :: Python :: 3.12
Requires-Dist: opencv-python (>=4.9.0.80,<5.0.0.0)
Requires-Dist: tqdm (>=4.66.1,<5.0.0)
